{
	"@metadata": {
		"authors": [
			"Espertus",
			"Kuwaity26",
			"Meno25",
			"Mgi92",
			"Test Create account",
			"Ahmed Mohsin",
			"ديفيد"
		]
	},
	"Games.name": "الالعاب الكتلية",
	"Games.puzzle": "أحجية",
	"Games.maze": "المتاهة",
	"Games.bird": "طائر",
	"Games.turtle": "السلحفاة",
	"Games.movie": "فلم",
	"Games.pondTutor": "مدرس البركة",
	"Games.pond": "البركة.",
	"Games.linesOfCode1": "لقد وجدت حل هذا المستوى بسطر واحد من جافا سكريبت :",
	"Games.linesOfCode2": "لقد تجاوزت هذا المستوى بـ 1% أسطر من جافا سكريبت :",
	"Games.nextLevel": "هل أنت جاهز للمستوى %1 ؟",
	"Games.finalLevel": "هل أنت مستعد للتحدي المقبل؟",
	"Games.linkTooltip": "احفظ وأعطي وصلة إلى البلوكات.",
	"Games.runTooltip": "قم بتشغيل برنامج كتبته.",
	"Games.runProgram": "شغِّل البرنامج",
	"Games.resetTooltip": "أوقف البرنامج وأعد تعيين المستوى.",
	"Games.resetProgram": "إعادة ضبط",
	"Games.help": "مساعدة",
	"Games.dialogOk": "موافق",
	"Games.dialogCancel": "إلغاء",
	"Games.catLogic": "منطق",
	"Games.catLoops": "الحلقات",
	"Games.catMath": "رياضيات",
	"Games.catText": "نص",
	"Games.catLists": "قوائم",
	"Games.catColour": "لون",
	"Games.catVariables": "متغيرات",
	"Games.catProcedures": "إجراءات",
	"Games.httpRequestError": "كانت هناك مشكلة مع هذا الطلب.",
	"Games.linkAlert": "مشاركة كود بلوكلي الخاص بك مع هذا الرابط:\n %1",
	"Games.hashError": "عذراً،ال '%1' لا تتوافق مع أي برنامج تم حفظه.",
	"Games.xmlError": "تعذر تحميل الملف المحفوظة الخاصة بك.  ربما تم إنشاؤه باستخدام إصدار مختلف من بلوكلي؟",
	"Games.listVariable": "قائمة",
	"Games.textVariable": "نص",
	"Games.breakLink": "بمجرد البدء في تحرير جافا سكريبت، لا يمكنك الذهاب إلى تعديل المجموعات. هل هذا جيد؟",
	"Games.blocks": "البلوكات",
	"Games.congratulations": "تهانينا!",
	"Games.helpAbort": "هذا المستوى صعب للغاية، هل ترغب في تخطي ذلك والذهاب إلى اللعبة القادمة؟يمكنك دائما العودة في وقت لاحق.",
	"Index.clear": "حذف كل حلولك؟",
	"Index.subTitle": "ألعاب لمبرمجي الغد.",
	"Index.moreInfo": "المزيد من المعلومات...",
	"Index.startOver": "هل ترغب في البدأ من جديد؟",
	"Index.clearData": "امح البيانات",
	"Puzzle.animal1": "بطة",
	"Puzzle.animal1Trait1": "ريش",
	"Puzzle.animal1Trait2": "منقار",
	"Puzzle.animal1HelpUrl": "https://en.wikipedia.org/wiki/Duck",
	"Puzzle.animal2": "قطة",
	"Puzzle.animal2Trait1": "شارب",
	"Puzzle.animal2Trait2": "فرو",
	"Puzzle.animal2HelpUrl": "https://en.wikipedia.org/wiki/Cat",
	"Puzzle.animal3": "نحلة",
	"Puzzle.animal3Trait1": "عسل",
	"Puzzle.animal3Trait2": "اللاسع",
	"Puzzle.animal3HelpUrl": "https://en.wikipedia.org/wiki/Bee",
	"Puzzle.animal4": "حلزون",
	"Puzzle.animal4Trait1": "صدفة",
	"Puzzle.animal4Trait2": "مخاط",
	"Puzzle.animal4HelpUrl": "https://en.wikipedia.org/wiki/Snail",
	"Puzzle.picture": "الصورة:",
	"Puzzle.legs": "أرجل:",
	"Puzzle.legsChoose": "اختر...",
	"Puzzle.traits": "سمة:",
	"Puzzle.error0": "ممتاز!\nكل الكتل %1 صحيحة.",
	"Puzzle.error1": "اقتربت! كتلة واحدة غير صحيح.",
	"Puzzle.error2": "%1 كتل غير صحيحة.",
	"Puzzle.tryAgain": "الكتلّة المُبرَزَة غير صحيحة.\nواصل المحاولة.",
	"Puzzle.checkAnswers": "تحقّق من الإجابات",
	"Puzzle.helpText": "لكل حيوان(بالأخضر) صل صورته و اختر عدد ارجله و اجمع سماته.",
	"Maze.moveForward": "تحرّك إلى الأمام",
	"Maze.turnLeft": "استدر إلى اليسار",
	"Maze.turnRight": "استدر الى اليمين",
	"Maze.doCode": "افعل",
	"Maze.elseCode": "والا",
	"Maze.helpIfElse": "كتل (إذا-وإلا) ستفعل شيئا محددا أو شيئا آخر.",
	"Maze.pathAhead": "إذا هناك مسار في الأمام",
	"Maze.pathLeft": "إذا كان المسار إلى اليسار",
	"Maze.pathRight": "إذا كان المسار إلى اليمين",
	"Maze.repeatUntil": "كرِّر حتى",
	"Maze.moveForwardTooltip": "يحرك اللاعب مسافة واحدة إلى الأمام.",
	"Maze.turnTooltip": "يدور اللاعب الى اليمين أو اليسار بمقدار 90 درجة.",
	"Maze.ifTooltip": "إذا كان هناك مسار في الاتجاه المحدد، انجز بعض الإجراءات.",
	"Maze.ifelseTooltip": "اذا كان هناك مسار في الاتجاه المٌحدد، لذا يٌمكنك تنفيذ أول كتلة من الأوامر. غير ذلك، قم بتنف",
	"Maze.whileTooltip": "قم بتكرار العملية حتى الوصول إلى نهاية النقطة المٌحددة.",
	"Maze.capacity0": "لديك %0 بلوكات متبقية.",
	"Maze.capacity1": "لديك %1 بلوك متبقي.",
	"Maze.capacity2": "لديك %2 بلوك متبقي.",
	"Maze.runTooltip": "يجعل اللاعب يقوم بما تقوله البلوكات.",
	"Maze.resetTooltip": " استرجاع اللاعب الى  بداية المتاهة.",
	"Maze.helpStack": "قم بعمل حركتين في آن واحد للآمام لمٌساعدتي للوصول الى الهدف.",
	"Maze.helpOneTopBlock": "في هذا المستوى, ستحتاج الى تجميع كل الكتل مع بعضها البعض في ساحة العمل البيضاء.",
	"Maze.helpRun": "قم بتشغيل البرنامج الخاص بك لرؤية ما يحدث.",
	"Maze.helpReset": "برنامجك لم يحل المتاهة.  اضغط 'إعادة' وحاول مرة أخرى.",
	"Maze.helpRepeat": "الوصول إلى نهاية المسار باستخدام فقط كتلتين. استخدم 'كرر حتى' لتشغيل الكتلة أكثر من مرة.",
	"Maze.helpCapacity": "لقد قمت باستخدام جميع الكتل في هذا المستوى. لعمل كتلة جديدة. عليك اولا مسح كتل موجودة.",
	"Maze.helpRepeatMany": "يٌمكنك ضبط اكثر من كتلة واحدة داخل كتلة 'كرر حتى'.",
	"Maze.helpSkins": "اختر لاعبك المفضل من هذه القائمة.",
	"Maze.helpIf": "كتلة 'إذا ستقوم بعمل شيء ما في حالة كن الشرط صحيحا. حاول الدوران إلى اليسار إذا كان هناك مسار إلى اليسار.",
	"Maze.helpMenu": "انقر على %1 في كتلة \"إذا\" لتغيير الحالة.",
	"Maze.helpWallFollow": "هل يمكنك حل هذه المتاهة المعقدة؟  حاول ان تلحق الجدار الأيسر.  للمبرمجين المتقدمين فقط!",
	"Bird.noWorm": "ليس لديه دودة",
	"Bird.heading": "يشير",
	"Bird.noWormTooltip": "الطير يريد الحصول على دودة.",
	"Bird.headingTooltip": "التحرك في اتجاه زاوية معينة: 0 إلى اليمين و90 على التوالي، إلخ",
	"Bird.helpHeading": "تغيير اتجاه الزاوية لجعل الطائر يحصل على دودة وأرض في عشه.",
	"Bird.helpHasWorm": "استخدم هذه المجموعة للتحرك في اتجاه واحد إذا كانت لديك دودة، أو اتجاه مختلف إذا لم تكن لديك دودة.",
	"Bird.helpElse": "انقر فوق الرمز لتعديل المجموعة \"if\".",
	"Bird.helpElseIf": "هذا المستوى يحتاج كلا من المجموعة \"else if\" والمجموعة  \"else'.",
	"Bird.helpAnd": "المجموعة \"and\" صحيحة فقط إذا كانت كل مدخلاتها صحيحة.",
	"Bird.helpMutator": "سحب المجموعة 'else' في المجموعة 'if'.",
	"Turtle.moveTooltip": "تحريك السلحفاة إلى الأمام أو إلى الخلف بمقدار محدد.",
	"Turtle.moveForward": "انتقل إلى الأمام بواسطة",
	"Turtle.moveBackward": "انتقل إلى الخلف بواسطة",
	"Turtle.turnTooltip": "تحويل السلحفاة الى الأيمن أو الأيسر بعدد معين من الدرجات.",
	"Turtle.turnRight": "استدر غلى اليمين بواسطة",
	"Turtle.turnLeft": "استدر إلى اليسار بواسطة",
	"Turtle.widthTooltip": "تغيير عرض القلم.",
	"Turtle.setWidth": "تعيين العرض إلى",
	"Turtle.colourTooltip": "تغيير لون القلم.",
	"Turtle.setColour": "تعيين اللون إلى",
	"Turtle.penTooltip": "يرفع أو يخفض القلم، ليتم إيقاف أو بدء الرسم.",
	"Turtle.penUp": "رفع القلم",
	"Turtle.penDown": "انزال القلم",
	"Turtle.turtleVisibilityTooltip": "جعل السلحفاة (دائرة وسهم) مرئية أو غير مرئية.",
	"Turtle.hideTurtle": "إخفاء السلحفاة",
	"Turtle.showTurtle": "إظهار السلحفاة",
	"Turtle.printHelpUrl": "https://en.wikipedia.org/wiki/Printing",
	"Turtle.printTooltip": "رسم/طباعة النص في في موقع اتجاه سلحفاة .",
	"Turtle.print": "إطبع",
	"Turtle.fontHelpUrl": "https://en.wikipedia.org/wiki/Font",
	"Turtle.fontTooltip": "يضبط الخط المستخدم بواسطة بلوك الطباعة.",
	"Turtle.font": "الخط",
	"Turtle.fontSize": "حجم الخط",
	"Turtle.fontNormal": "عادي",
	"Turtle.fontBold": "غامق",
	"Turtle.fontItalic": "مائل",
	"Turtle.submitDisabled": "تشغيل البرنامج حتى يتوقف، ثم يمكنك تقديم الرسم إلى المعرض.",
	"Turtle.galleryTooltip": "فتح معرض للرسومات على رديت.",
	"Turtle.galleryMsg": "انظر معرض الصور",
	"Turtle.submitTooltip": "إرسال الرسم إلى رديت.",
	"Turtle.submitMsg": "إرسال إلى معرض",
	"Turtle.helpUseLoop": "حلك يعمل، لكن يمكنك أن تقوم بالأفضل.",
	"Turtle.helpUseLoop3": "رسم الشكل في ثلاث مجموعات فقط.",
	"Turtle.helpUseLoop4": "رسم النجم في أربع مجموعات فقط.",
	"Turtle.helpText1": "إنشاء البرنامج الذي يرسم مربعا.",
	"Turtle.helpText2": "تغيير البرنامج لرسم خماسي الأضلاع بدلا من المربع.",
	"Turtle.helpText3a": "هناك مجموعة جديدة تسمح لك بتغيير اللون:",
	"Turtle.helpText3b": "إرسم نجمة صفراء.",
	"Turtle.helpText4a": "هناك مجموعة جديدة تسمح لك برفع القلم بعيدا عن الورقة عند الانتقال:",
	"Turtle.helpText4b": "رسم نجمة صفراء صغيرة، ثم رسم خط فوقها.",
	"Turtle.helpText5": "بدلا من نجم واحد، هل يمكنك رسم النجوم الأربعة على شكل مربع؟",
	"Turtle.helpText6": "رسم ثلاثة نجوم صفراء، وخط واحد أبيض.",
	"Turtle.helpText7": "رسم النجوم، ثم رسم أربعة خطوط بيضاء.",
	"Turtle.helpText8": "رسم 360 خطًا بيضاء سيبدون كالقمر الكامل.",
	"Turtle.helpText9": "هل يمكنك إضافة دائرة سوداء بحيث يصبح القمر هلالا؟",
	"Turtle.helpText10": "ارسم أي شيء تريده; كنت قد حصلت على عدد كبير من القطع الجديدة التي يمكن استكشافها.استمتع!",
	"Turtle.helpToolbox": "اختر تصنيفًا لرؤية المجموعة.",
	"Turtle.catTurtle": "السلحفاة",
	"Movie.x": "س",
	"Movie.y": "ص",
	"Movie.x1": "بداية س",
	"Movie.y1": "بداية ص",
	"Movie.x2": "نهاية س",
	"Movie.y2": "نهاية ص",
	"Movie.radius": "نصف القطر",
	"Movie.width": "العرض",
	"Movie.height": "الارتفاع",
	"Movie.circleTooltip": "إرسم دائرةفي المكان المحدد وبنصف القطر المحدد.",
	"Movie.circleDraw": "دائرة",
	"Movie.rectTooltip": "إرسم مستطيل في المكان المحدد وبالطول والعرض المحددين.",
	"Movie.rectDraw": "مستطيل",
	"Movie.lineTooltip": "إرسم خط من نقطة الى نقطة اخرى وبالعرض المحدد.",
	"Movie.lineDraw": "خط",
	"Movie.timeTooltip": "إرجاع الوقت الحالي في الرسوم المتحركة (0-100).",
	"Movie.colourTooltip": "تغيير لون القلم.",
	"Movie.setColour": "تعيين اللون إلى",
	"Movie.submitDisabled": "الفيلم لا يتحرك; استخدم مجموعة لصنع شيئا مثيرا للاهتمام، ثم يمكنك تقديم فيلمك إلى المعرض.",
	"Movie.galleryTooltip": "فتح معرض للأفلام على رديت.",
	"Movie.galleryMsg": "انظر معرض الصور",
	"Movie.submitTooltip": "إرسال الرسم إلى رديت.",
	"Movie.submitMsg": "إرسال إلى معرض",
	"Movie.helpText1": "استخدام الأشكال البسيطة لرسم هذا الشخص.",
	"Movie.helpText2a": "هذا المستوى هو فيلم.إذا كنت ترغب في الكرة الحمراء للتدوير عبر الشاشة، اضغط على زر تشغيل المعاينة.",
	"Movie.helpText4": "استخدام ما تعلمته في المستوى السابق لصنع الكرات الخضراء الأربع التي تتحرك في جميع الاتجاهات الأربعة.",
	"Movie.helpText5": "جعل تحرك رأس الفأرة سهلًا.هل يمكنك العمل على الرياضيات لجعل آذان تتحرك أيضا؟",
	"Movie.helpText6": "مجرد معرفة ماذا تفعل نهايات الخط.",
	"Movie.helpText7": "الصيغة الرياضية لهبوط هذه الكرة معقدة، وهنا يكمن الجواب:",
	"Movie.helpText8": "استخدم مجموعة \"if\" لرسم الكرات الحمراء والزرقاء في النصف الأول من الفيلم، ثم ارسم الكرة الخضراء في النصف الثاني من الفيلم.",
	"Movie.helpText9": "هل يمكنك صنع الكرة التي تتبع السلك؟وقد تم بالفعل سحب السلك بالنسبة لك. يمكنك القيام بذلك مرة واحدة، يمكنك أن تفعل أي شيء.",
	"Movie.helpText10": "اصنع فيلم من أي شيء تريده; كنت قد حصلت على عدد كبير من القطع الجديدة التي يمكن استكشافها.استمتع!",
	"Pond.scanTooltip": "مسح للأعداء. تحديد الاتجاه (0-360). يعيد المسافة إلى أقرب العدو في هذا الاتجاه. يعود إلى ما لا نهاية إذا لم يجد أي عدو.",
	"Pond.cannonTooltip": "إطلاق المدفع. تحديد الاتجاه (0-360) ومجموعة (0-70).",
	"Pond.swimTooltip": "السباحة إلى الأمام. تحديد الاتجاه (0-360).",
	"Pond.stopTooltip": "أوقف السباحة. اللاعب يتباطأ حتى يتوقف.",
	"Pond.healthTooltip": "يعيد الصحة الحالية اللاعب (0 ميت، 100 غير صحي).",
	"Pond.speedTooltip": "يرجع السرعة الحالية للاعب (0 توقف، 100 سرعة كاملة).",
	"Pond.locXTooltip": "يرجع تنسيق اللاعب X (0 الحافة اليسرى، و 100 الحافة اليمنى).",
	"Pond.locYTooltip": "يرجع تنسيق اللاعب Y (0 الحافة السفلية، و 100 الحافة العلوية).",
	"Pond.docsTooltip": "عرض وثائق اللغة.",
	"Pond.documentation": "توثيق",
	"Pond.playerName": "اللاعب",
	"Pond.targetName": "الهدف",
	"Pond.pendulumName": "رقاص الساعة",
	"Pond.scaredName": "خائف",
	"Pond.helpUseScan": "حلك يعمل، لكن يمكنك أن تقوم بالأفضل. استخدم 'مسح' لتقول للمدفع إلى أي مدى يطلق النار.",
	"Pond.helpText1": "استخدم الأمر \"مدفع\" لضرب الهدف. المعلمة الأولى زاوية، والمعلمة الثانية مدى. جد التركيبة الصحيحة.",
	"Pond.helpText2": "يحتاج هذا الهدف لأن يتم ضربه عدة مرات، استخدم حلقة \"while true)\" لتفعل شيئا لأجل غير مسمى.",
	"Pond.helpText3a": "هذا الخصم يتحرك ذهابا وإيابا، مما يجعل من الصعب ضربه. التعبير \"مسح\" يعيد المدى المحدد لمنافسه في الاتجاه المحدد.",
	"Pond.helpText3b": "هذا النطاق هو بالضبط ما يحتاجه \"مدفع\" الأوامر لإطلاق النار بدقة.",
	"Pond.helpText4": "هذا الخصم بعيد جدا لاستخدام مدفع (التي لديها حدود 70 مترا)، بدلا من ذلك، استخدم الأمر 'سباحة' لبدء السباحة نحو الخصم وتحطيمه.",
	"Pond.helpText5": "هذا الخصم هو أيضا بعيد لاستخدام المدفع، ولكنك أضعف من أن تنجو من التصادم; اسبح نحو الخصم بينما أنت في وضع أفقي أقل من 50، ثم \"قف\" واستخدم المدفع.",
	"Pond.helpText6": "وهذا الخصم الابتعاد عندما ضُرِب، اسبح نحوه إذا كان خارج النطاق (70 متر).",
	"Pond.rabbitName": "أرنب",
	"Pond.counterName": "العداد",
	"Pond.rookName": "غراب",
	"Pond.sniperName": "قناص"
}
